elit/__init__.py
elit/benchmark.py
elit/config.py
elit/dataset.py
elit/eval.py
elit/structure.py
elit/version.py
elit/cli/__init__.py
elit/cli/__main__.py
elit/cli/base.py
elit/cli/component.py
elit/component/__init__.py
elit/component/base.py
elit/component/cnn.py
elit/component/doc_classifier.py
elit/component/lemmatizer.py
elit/component/morph_analyzer.py
elit/component/mx.py
elit/component/nlp.py
elit/component/rnn.py
elit/component/sentiment.py
elit/component/tokenizer.py
elit/component/dep/__init__.py
elit/component/dep/dep_cli.py
elit/component/dep/dependency_parser.py
elit/component/dep/common/__init__.py
elit/component/dep/common/config.py
elit/component/dep/common/data.py
elit/component/dep/common/exponential_scheduler.py
elit/component/dep/common/k_means.py
elit/component/dep/common/savable.py
elit/component/dep/common/tarjan.py
elit/component/dep/common/utils.py
elit/component/dep/parser/__init__.py
elit/component/dep/parser/biaffine_parser.py
elit/component/dep/parser/dep_parser.py
elit/component/dep/parser/evaluate/__init__.py
elit/component/dep/parser/evaluate/evaluate.py
elit/component/embedding/__init__.py
elit/component/embedding/base.py
elit/component/embedding/contextual_string_embedding.py
elit/component/embedding/fasttext.py
elit/component/embedding/token.py
elit/component/embedding/word2vec.py
elit/component/language_models/__init__.py
elit/component/language_models/contextual_string_model.py
elit/component/lemmatization/__init__.py
elit/component/lemmatization/english/__init__.py
elit/component/lemmatization/english/inflection.py
elit/component/lemmatization/english/suffix_group.py
elit/component/lemmatization/english/suffix_rule.py
elit/component/sdp/__init__.py
elit/component/sdp/biaffine_parser.py
elit/component/sdp/biaffine_sdp.py
elit/component/sdp/data.py
elit/component/sdp/sdp_cli.py
elit/component/sdp/sdp_parser.py
elit/component/tagger/__init__.py
elit/component/tagger/corpus.py
elit/component/tagger/embeddings.py
elit-0.1.35.dist-info/LICENSE
elit-0.1.35.dist-info/METADATA
elit-0.1.35.dist-info/WHEEL
elit-0.1.35.dist-info/top_level.txt
elit-0.1.35.dist-info/RECORD
