Metadata-Version: 2.1
Name: elit
Version: 0.1.35
Summary: ELIT: Evolution of Language and Information Technology
Home-page: https://github.com/elitcloud/elit
Author: Emory NLP
Author-email: jinho.choi@emory.edu
License: Apache 2.0
Download-URL: https://github.com/elitcloud/elit/tree/master
Platform: UNKNOWN
Classifier: Development Status :: 3 - Alpha
Classifier: Intended Audience :: Science/Research
Classifier: Intended Audience :: Developers
Classifier: License :: OSI Approved :: Apache Software License
Classifier: Programming Language :: Python :: 3 :: Only
Classifier: Programming Language :: Python :: 3.6
Classifier: Topic :: Scientific/Engineering :: Artificial Intelligence
Classifier: Topic :: Scientific/Engineering :: Information Analysis
Classifier: Operating System :: POSIX
Classifier: Operating System :: Unix
Classifier: Operating System :: MacOS
Requires-Dist: mxnet (>=1.4.1)
Requires-Dist: argparse (==1.4.0)
Requires-Dist: numpy (==1.14.5)
Requires-Dist: gluonnlp (==0.6.0)
Requires-Dist: tqdm (==4.26.0)
Requires-Dist: gensim (==3.6.0)
Requires-Dist: marisa-trie (==0.7.5)
